cycleops/__main__.py
cycleops/auth.py
cycleops/client.py
cycleops/environments.py
cycleops/exceptions.py
cycleops/hostgroups.py
cycleops/hosts.py
cycleops/services.py
cycleops/setups.py
cycleops/stacks.py
cycleops/units.py
cycleops/utils.py
cycleops-0.8.0.dist-info/LICENSE
cycleops-0.8.0.dist-info/METADATA
cycleops-0.8.0.dist-info/WHEEL
cycleops-0.8.0.dist-info/entry_points.txt
cycleops-0.8.0.dist-info/RECORD
