Metadata-Version: 2.1
Name: cycleops
Version: 0.8.0
Summary: The official command line interface for Cycleops
License: MIT
Author: Thanasis Parathyras
Author-email: aparathyras@stackmasters.eu
Requires-Python: >=3.11,<4.0
Classifier: License :: OSI Approved :: MIT License
Classifier: Programming Language :: Python :: 3
Classifier: Programming Language :: Python :: 3.11
Requires-Dist: requests (>=2.28.2,<3.0.0)
Requires-Dist: sec (>=0.3.0,<0.4.0)
Requires-Dist: typer[all] (>=0.7.0,<0.8.0)
Requires-Dist: websockets (>=12.0,<13.0)
